README.rst
console_tool.py
setup.py
console_tool.egg-info/PKG-INFO
console_tool.egg-info/SOURCES.txt
console_tool.egg-info/dependency_links.txt
console_tool.egg-info/requires.txt
console_tool.egg-info/top_level.txt