Metadata-Version: 1.1
Name: console-tool
Version: 1.2.4
Summary: 提供创建命令行程序工具的模块,包含Console类。A module for creating command line programs.
Home-page: https://github.com/qfcy/Python/blob/main/Terminal/console_tool.py
Author: 七分诚意 qq:3076711200
Author-email: 3076711200@qq.com
License: UNKNOWN
Keywords: terminal,command-line,console,cmd,控制台窗口
Platform: UNKNOWN
Classifier: Environment :: Console
Classifier: Programming Language :: Python :: 3
Classifier: Topic :: Terminals
